setup.py
ppp_french_parser/__init__.py
ppp_french_parser/config.py
ppp_french_parser/parser.py
ppp_french_parser/requesthandler.py
ppp_french_parser.egg-info/PKG-INFO
ppp_french_parser.egg-info/SOURCES.txt
ppp_french_parser.egg-info/dependency_links.txt
ppp_french_parser.egg-info/requires.txt
ppp_french_parser.egg-info/top_level.txt