Metadata-Version: 1.1
Name: ppp-french-parser
Version: 0.1.4
Summary: Parser of the French language for the PPP.
Home-page: https://github.com/ProjetPP
Author: Valentin Lorentz
Author-email: valentin.lorentz+ppp@ens-lyon.org
License: MIT
Platform: UNKNOWN
Classifier: Environment :: No Input/Output (Daemon)
Classifier: Development Status :: 1 - Planning
Classifier: Intended Audience :: System Administrators
Classifier: License :: OSI Approved :: MIT License
Classifier: Operating System :: OS Independent
Classifier: Programming Language :: Python :: 3
Classifier: Programming Language :: Python :: 3.2
Classifier: Programming Language :: Python :: 3.3
Classifier: Programming Language :: Python :: 3.4
Classifier: Topic :: Internet :: WWW/HTTP :: WSGI :: Application
Classifier: Topic :: Software Development :: Libraries
